LICENSE
MANIFEST.in
README.md
setup.py
bin/pjsipcheck
etc/pjsipcheck.conf
init.d/pjsipcheckd
pjsipcheck/__init__.py
pjsipcheck/pjsipcheck.py
pjsipcheck/settings.py
pjsipcheck/templates/block_email.html
pjsipcheck/templates/block_email.txt
pjsipcheck/utils/__init__.py
pjsipcheck/utils/attacks.py
pjsipcheck/utils/config.py
pjsipcheck/utils/db.py
pjsipcheck/utils/iptables.py
pjsipcheck/utils/logger.py
pjsipcheck/utils/sendmail.py
pjsipcheck/utils/tools.py
py_asterisk_banner.egg-info/PKG-INFO
py_asterisk_banner.egg-info/SOURCES.txt
py_asterisk_banner.egg-info/dependency_links.txt
py_asterisk_banner.egg-info/not-zip-safe
py_asterisk_banner.egg-info/requires.txt
py_asterisk_banner.egg-info/top_level.txt