Metadata-Version: 1.1
Name: py-asterisk-banner
Version: 1.0.2
Summary: Baneador de IPs en Asterisk con soporte para SIP y PJSIP
Home-page: https://github.com/savsgio/py-asterisk-banner.git
Author: Sergio Andres Virviescas Santana
Author-email: developersavsgio@gmail.com
License: GPL
Platform: UNKNOWN
Classifier: Development Status :: 7 - Inactive
Classifier: Programming Language :: Python :: 3
Classifier: Topic :: Utilities
